aiida_conda_scheduler/__init__.py
aiida_conda_scheduler/schedulers.py
aiida_conda_scheduler-0.1.0.dist-info/entry_points.txt
aiida_conda_scheduler-0.1.0.dist-info/LICENSE
aiida_conda_scheduler-0.1.0.dist-info/WHEEL
aiida_conda_scheduler-0.1.0.dist-info/METADATA
aiida_conda_scheduler-0.1.0.dist-info/RECORD
