Metadata-Version: 2.1
Name: aiida_conda_scheduler
Version: 0.1.0
Summary: AiiDA scheduler plugins that allow for `conda run`.
Keywords: aiida,plugin
Author-email: Chris Sewell <chrisj_sewell@hotmail.com>
Requires-Python: >=3.7
Classifier: Development Status :: 3 - Alpha
Classifier: License :: OSI Approved :: MIT License
Classifier: Programming Language :: Python
Classifier: Intended Audience :: Science/Research
Classifier: Natural Language :: English
Classifier: Framework :: AiiDA
Requires-Dist: aiida-core>=1.0,<3
Requires-Dist: coverage[toml] ; extra == "testing"
Requires-Dist: pytest~=6.0 ; extra == "testing"
Requires-Dist: pytest-cov ; extra == "testing"
Project-URL: Source, https://github.com/chrisjsewell/aiida-conda-scheduler
Provides-Extra: testing
